setup.py
distributions/Binomialdistribution.py
distributions/Gaussiandistribution.py
distributions/Generaldistribution.py
distributions/__init__.py
probability_dsnd_2019.egg-info/PKG-INFO
probability_dsnd_2019.egg-info/SOURCES.txt
probability_dsnd_2019.egg-info/dependency_links.txt
probability_dsnd_2019.egg-info/not-zip-safe
probability_dsnd_2019.egg-info/top_level.txt