Metadata-Version: 1.0
Name: probability-dsnd-2019
Version: 0.1
Summary: Gaussian and Binomial distributions
Home-page: UNKNOWN
Author: Jean-Sebastien Provost
Author-email: UNKNOWN
License: UNKNOWN
Platform: UNKNOWN
